tspmetrics/__init__.py
tspmetrics/__meta__.py
tspmetrics/alt.py
tspmetrics/amplitude.py
tspmetrics/classification.py
tspmetrics/flags.py
tspmetrics/labels.py
tspmetrics/thaw_depth_duration.py
tspmetrics/thermal_integral.py
tspmetrics/zero_amplitude.py
tspmetrics/demos/demo_data/B755-Arctic_Village-Dataset.csv
tspmetrics/demos/demo_data/soil.txt
tspmetrics-0.0.5.dist-info/METADATA
tspmetrics-0.0.5.dist-info/WHEEL
tspmetrics-0.0.5.dist-info/top_level.txt
tspmetrics-0.0.5.dist-info/RECORD
